multi_med_image_ml/DataBaseWrapper.py
multi_med_image_ml/MedImageLoader.py
multi_med_image_ml/MultiInputTester.py
multi_med_image_ml/MultiInputTrainer.py
multi_med_image_ml/Records.py
multi_med_image_ml/TripletLoss.py
multi_med_image_ml/__init__.py
multi_med_image_ml/dcm2niix
multi_med_image_ml/models.py
multi_med_image_ml/utils.py
multi_med_image_ml-1.0.1.dist-info/METADATA
multi_med_image_ml-1.0.1.dist-info/WHEEL
multi_med_image_ml-1.0.1.dist-info/RECORD
