Metadata-Version: 2.4
Name: multi_med_image_ml
Version: 1.0.1
Summary: Deep learning library to encode multiple brain images and other electronic health record data in disease detection.
Project-URL: Homepage, https://github.com/mleming/MultiMedImageML
Author-email: Matt Leming <mleming@mgh.harvard.edu>
Maintainer-email: Matt Leming <mleming@mgh.harvard.edu>
License: MIT License
Keywords: biomedical,deep learning,ehr,machine learning,mri,pytorch
Requires-Python: >=3.8
Requires-Dist: adjusttext
Requires-Dist: datefinder
Requires-Dist: dcm2niix
Requires-Dist: dicom2nifti
Requires-Dist: gdown>=4.4.0
Requires-Dist: general-class-balancer
Requires-Dist: matplotlib>=3.5.0
Requires-Dist: monai>=1.3.1
Requires-Dist: nibabel>=5.2.1
Requires-Dist: numpy>=1.22.0
Requires-Dist: opencv-python>=4.5.4
Requires-Dist: pillow>=9.3.0
Requires-Dist: platformdirs
Requires-Dist: pyclustering
Requires-Dist: pydicom>=2.4.4
Requires-Dist: python-dateutil
Requires-Dist: requests>=2.28.1
Requires-Dist: scikit-image>=0.19.3
Requires-Dist: scikit-learn>=1.2.0
Requires-Dist: scipy>=1.9.3
Requires-Dist: torch>=1.13.0
Requires-Dist: torchvision>=0.14.0
